<?xml version="1.0"?>
<view xmlns:xsi="http://www.w3.org/2001/XMLSchema-instance" xsi:noNamespaceSchemaLocation="urn:magento:framework:Config/etc/view.xsd">
    <media>
        <images module="Magento_Catalog">
            <image id="product_page_image_large" type="image"/>
            <image id="product_page_image_medium" type="image">
                <width>400</width>
                <height>400</height>
            </image>
            <image id="product_page_image_small" type="thumbnail">
                <width>65</width>
                <height>65</height>
            </image>
            <image id="related_products_list" type="small_image">
                <width>234</width>
                <height>234</height>
            </image>
            <image id="recently_viewed_datasource" type="small_image">
                <width>238</width>
                <height>238</height>
            </image>
        </images>
    </media>
    <!-- Gallery and magnifier theme settings. Start -->
    <vars module="Magento_Catalog">
        <var name="gallery">
            <var name="navdir">vertical</var> <!-- Sliding direction of thumbnails (horizontal/vertical) -->
            <var name="navarrows">false</var> <!-- Turn on/off on the thumbs navigation sides arrows(true/false) -->
            <var name="navtype">thumbs</var> <!-- Sliding type of thumbnails (slides/thumbs) -->
            <var name="arrows">false</var> <!-- Turn on/off arrows on the sides preview (true/false) -->
            <var name="loop">false</var> <!-- Gallery navigation loop (true/false) -->
            <var name="keyboard">false</var> <!-- Turn on/off keyboard arrows navigation (true/false) -->
            <var name="navtype">thumbs</var> <!-- Sliding type of thumbnails (slides/thumbs) -->
            <var name="fullscreen">
                <var name="nav">thumbs</var> <!-- Fullscreen navigation style (false/thumbs/dots) -->
                <var name="loop">true</var> <!-- Fullscreen navigation loop (true/false/null) -->
                <var name="arrows">false</var> <!-- Turn on/off arrows on the sides preview in fullscreen (true/false/null) -->
                <var name="caption">false</var> <!-- Display alt text as image title in fullscreen(true/false) -->
                <var name="navdir">horizontal</var> <!--Sliding direction of thumbnails in fullscreen(horizontal/vertical)  -->
                <var name="navtype">slides</var> <!-- Sliding type of thumbnails (slides/thumbs) -->
                <var name="transition">
                    <var name="effect">dissolve</var> <!-- Sets transition effect for slides changing (slide/crossfade/dissolve) -->
                    <var name="duration">500</var> <!-- Sets transition duration in ms -->
                </var>
            </var>
        </var>
    </vars>
</view>
